apimonitor/__init__.py
apimonitor/cli.py
apimonitor/config.py
apimonitor/dashboard.py
apimonitor/endpoint.py
apimonitor/exceptions.py
apimonitor/models.py
apimonitor/monitor.py
apimonitor/notifications.py
apimonitor-1.0.0.dist-info/METADATA
apimonitor-1.0.0.dist-info/WHEEL
apimonitor-1.0.0.dist-info/entry_points.txt
apimonitor-1.0.0.dist-info/top_level.txt
apimonitor-1.0.0.dist-info/RECORD
